OrbbecSDKConfig.xml
libOrbbecSDK.so
libOrbbecSDK.so.2
libOrbbecSDK.so.2.5.2
pyorbbecsdk.cpython-313-x86_64-linux-gnu.so
extensions/depthengine/libdepthengine.so
extensions/depthengine/libdepthengine.so.2.0
extensions/filters/libFilterProcessor.so
extensions/filters/libob_priv_filter.so
extensions/firmwareupdater/libfirmwareupdater.so
extensions/frameprocessor/libob_frame_processor.so
obtest.libs/libEGL-12f84b62.so.1.0.0
obtest.libs/libGLdispatch-2ac91fdd.so.0.0.0
pyorbbecsdk/config/OrbbecSDKConfig.md
pyorbbecsdk/config/OrbbecSDKConfig.xml
pyorbbecsdk/config/multi_device_sync_config.json
pyorbbecsdk/examples/.gitkeep
pyorbbecsdk/examples/README.md
pyorbbecsdk/examples/callback.py
pyorbbecsdk/examples/color.py
pyorbbecsdk/examples/coordinate_transform.py
pyorbbecsdk/examples/depth.py
pyorbbecsdk/examples/depth_work_mode.py
pyorbbecsdk/examples/device_firmware_update.py
pyorbbecsdk/examples/device_optional_depth_presets_update.py
pyorbbecsdk/examples/enumerate.py
pyorbbecsdk/examples/hdr.py
pyorbbecsdk/examples/hot_plug.py
pyorbbecsdk/examples/hw_d2c_align.py
pyorbbecsdk/examples/imu.py
pyorbbecsdk/examples/infrared.py
pyorbbecsdk/examples/laser_interleave.py
pyorbbecsdk/examples/logger.py
pyorbbecsdk/examples/metadata.py
pyorbbecsdk/examples/multi_device.py
pyorbbecsdk/examples/multi_streams.py
pyorbbecsdk/examples/net_device.py
pyorbbecsdk/examples/playback.py
pyorbbecsdk/examples/point_cloud.py
pyorbbecsdk/examples/post_processing.py
pyorbbecsdk/examples/preset.py
pyorbbecsdk/examples/quick_start.py
pyorbbecsdk/examples/recorder.py
pyorbbecsdk/examples/requirements.txt
pyorbbecsdk/examples/save_image_to_disk.py
pyorbbecsdk/examples/sync_align.py
pyorbbecsdk/examples/two_devices_sync.py
pyorbbecsdk/examples/utils.py
pyorbbecsdk/examples/object_detection/README.md
pyorbbecsdk/examples/object_detection/coco.names
pyorbbecsdk/examples/object_detection/object_detection_sw_align.py
obtest-2.0.14.dist-info/METADATA
obtest-2.0.14.dist-info/WHEEL
obtest-2.0.14.dist-info/top_level.txt
obtest-2.0.14.dist-info/RECORD
obtest-2.0.14.dist-info/licenses/LICENSE
