Metadata-Version: 2.4
Name: obtest
Version: 2.0.14
Summary: pyorbbecsdk is a python wrapper for the OrbbecSDK
Author: zhonghong
Author-email: zhonghong@orbbec.com
License-File: LICENSE
Dynamic: author
Dynamic: author-email
Dynamic: license-file
Dynamic: summary
